basado_derivada/__init__.py
basado_derivada/metodo_biseccion.py
basado_derivada/metodo_secante.py
basado_derivada/newton_Raphson.py
eliminacion_regiones/__init__.py
eliminacion_regiones/fibonacci.py
eliminacion_regiones/intervalos_mitad.py
eliminacion_regiones/seleccion_dorada.py
funcion/__init__.py
funcion/funciones_multivariables.py
funcion/funciones_una_variable.py
metodo_directos/__init__.py
metodo_directos/caminata_aleatoria.py
metodo_directos/hooke_Jeeves.py
metodo_directos/nelder_Mead.py
metodos_gradiente/__init__.py
metodos_gradiente/cauchy.py
metodos_gradiente/fletcher_Reeves.py
metodos_gradiente/newton.py
metodos_multivariable/__init__.py
metodos_multivariable/caminata_aleatoria.py
metodos_multivariable/cauchy.py
metodos_multivariable/fletcher_Reeves.py
metodos_multivariable/hooke_Jeeves.py
metodos_multivariable/nelder_Mead.py
metodos_multivariable/newton.py
metodos_una_variable/__init__.py
metodos_una_variable/fibonacci.py
metodos_una_variable/intervalos_mitad.py
metodos_una_variable/metodo_biseccion.py
metodos_una_variable/metodo_secante.py
metodos_una_variable/newton_Raphson.py
metodos_una_variable/seleccion_dorada.py
multivariadas/__init__.py
multivariadas/metodo_directos/__init__.py
multivariadas/metodo_directos/caminata_aleatoria.py
multivariadas/metodo_directos/hooke_Jeeves.py
multivariadas/metodo_directos/nelder_Mead.py
multivariadas/metodos_gradiente/__init__.py
multivariadas/metodos_gradiente/cauchy.py
multivariadas/metodos_gradiente/fletcher_Reeves.py
multivariadas/metodos_gradiente/newton.py
una_variable/__init__.py
una_variable/basado_derivada/__init__.py
una_variable/basado_derivada/metodo_biseccion.py
una_variable/basado_derivada/metodo_secante.py
una_variable/basado_derivada/newton_Raphson.py
una_variable/eliminacion_regiones/__init__.py
una_variable/eliminacion_regiones/fibonacci.py
una_variable/eliminacion_regiones/intervalos_mitad.py
una_variable/eliminacion_regiones/seleccion_dorada.py
optimizacion_Cristopher-0.1.dist-info/METADATA
optimizacion_Cristopher-0.1.dist-info/WHEEL
optimizacion_Cristopher-0.1.dist-info/top_level.txt
optimizacion_Cristopher-0.1.dist-info/RECORD
