Metadata-Version: 2.1
Name: optimizacion_Cristopher
Version: 0.1
Summary: Proyecto de optimizacion con varios codigos para dicha optimizacion
Home-page: https://github.com/CristopherAlejandoRuizBouchez/Proyecto-Optimizacion
Author: Cristopher Alejandro Ruiz Bouchez
Author-email: cristopherruizbouchez@gmail.com
